gmn-1.4.1.dist-info/METADATA
gmn-1.4.1.dist-info/WHEEL
gmn-1.4.1.dist-info/entry_points.txt
gmn-1.4.1.dist-info/licenses/LICENSE
gmn/.gitignore
gmn/Auxiliary.py
gmn/CLI_Parser.py
gmn/Common.py
gmn/ConfigParser.py
gmn/Forecast.py
gmn/GMN.py
gmn/Generate.py
gmn/Network.py
gmn/Node.py
gmn/Parameters.py
gmn/Plot.py
gmn/__init__.py
gmn-1.4.1.dist-info/RECORD
