Metadata-Version: 2.1
Name: gmn
Version: 1.4.1
Summary: Generative Manifold Networks
Author-Email: Joseph Park <JosephPark@IEEE.org>, Gerald Pao <Gerald.Pao@OIST.jp>
Classifier: Programming Language :: Python :: 3
Classifier: License :: Free For Educational Use
Classifier: Operating System :: OS Independent
Project-URL: Homepage, https://github.com/NonlinearDynamicsDSU/gmn
Project-URL: Documentation, https://nonlineardynamicsdsu.github.io/gmn/
Project-URL: Issues, https://github.com/NonlinearDynamicsDSU/gmn/issues
Requires-Python: >=3.10
Requires-Dist: pyEDM>=2.1.0
Requires-Dist: networkx>=3.0
Requires-Dist: pandas>=2.0
Requires-Dist: pyarrow
Requires-Dist: numpy
Requires-Dist: matplotlib
Requires-Dist: scikit-learn
